pyykov/__init__.py
pyykov/markov_link.py
pyykov/possible_follow_up.py
pyykov/pyykov-test.py
pyykov/pyykov.py
pyykov/pyykov_test.py
pyykov-1.1.dist-info/METADATA
pyykov-1.1.dist-info/WHEEL
pyykov-1.1.dist-info/top_level.txt
pyykov-1.1.dist-info/RECORD
