Metadata-Version: 2.1
Name: pyykov
Version: 1.1
Summary: Markov generator for python.
Home-page: https://github.com/maymike321/pyykov
Author: Michael May
Author-email: yamekim@comcast.net
License: MIT
Platform: UNKNOWN
